effpassphrase/__init__.py
effpassphrase/eff_large_wordlist.txt
effpassphrase-0.1.1.dist-info/LICENSE
effpassphrase-0.1.1.dist-info/METADATA
effpassphrase-0.1.1.dist-info/WHEEL
effpassphrase-0.1.1.dist-info/entry_points.txt
effpassphrase-0.1.1.dist-info/top_level.txt
effpassphrase-0.1.1.dist-info/RECORD
