Metadata-Version: 2.1
Name: effpassphrase
Version: 0.1.1
Summary: Uses the EFF's long word list to generate a high entropy passphrase.
Home-page: https://github.com/michael-lorenzo/effpassphrase
Author: Michael Lorenzo
Author-email: python@michael-lorenzo.com
License: UNKNOWN
Platform: UNKNOWN
Classifier: Programming Language :: Python :: 3
Classifier: License :: OSI Approved :: Apache Software License
Classifier: Operating System :: OS Independent
Requires-Python: >=3.6
License-File: LICENSE
Requires-Dist: click
